auth2guard/__init__.py
auth2guard/sentinel.py
auth2guard-0.4.0.dist-info/LICENSE
auth2guard-0.4.0.dist-info/METADATA
auth2guard-0.4.0.dist-info/WHEEL
auth2guard-0.4.0.dist-info/RECORD
