Metadata-Version: 2.1
Name: auth2guard
Version: 0.4.0
Summary: OAuth 2.0 scope validator
License: Apache-2.0
Author: Marco Sievers de Almeida Ximit Gaia
Author-email: im.ximit@gmail.com
Requires-Python: >=3.10,<4.0
Classifier: License :: OSI Approved :: Apache Software License
Classifier: Programming Language :: Python :: 3
Classifier: Programming Language :: Python :: 3.10
Classifier: Programming Language :: Python :: 3.11
Requires-Dist: jwt (>=1.3.1,<2.0.0)
